isfreader/__init__.py
isfreader/__meta__.py
isfreader/py_isfreader.py
isfreader-1.2.0.dist-info/METADATA
isfreader-1.2.0.dist-info/WHEEL
isfreader-1.2.0.dist-info/licenses/LICENSE
isfreader-1.2.0.dist-info/RECORD
